{
    "ticker": "ACM",
    "company_name": "AECOM",
    "universe_added_date": "2026-05-18",
    "financial_raw_metrics": {
        "sector": "Industrials",
        "industry": "Engineering & Construction",
        "market_cap_usd": 9019738112,
        "profitability": {
            "gross_margin_ttm": 0.077259995,
            "operating_margin_ttm": 0.06701,
            "net_margin_ttm": 0.03164,
            "operating_margin_trend_3yr": 0.012316616256600944
        },
        "returns_on_capital": {
            "roe_ttm": 0.28608,
            "roa_ttm": 0.056789998,
            "roic_ttm": null
        },
        "cash_flow": {
            "fcf_margin_ttm": 0.027773536022229216,
            "fcf_to_net_income_ttm": 0.7032326921398457,
            "ocf_cagr_3yr": 0.04808115563891224
        },
        "balance_sheet": {
            "debt_to_equity": 1.3520599999999998,
            "net_debt_to_ebitda": 1.8037749099269231,
            "current_ratio": 1.105,
            "interest_coverage": 5.967710955812136,
            "total_debt_usd": 3346927104,
            "total_cash_usd": 1043556992
        },
        "growth": {
            "revenue_growth_1yr": 0.008,
            "revenue_cagr_3yr": 0.07071992371075209,
            "eps_growth_1yr": 0.285,
            "eps_cagr_3yr": 0.2183767452608747,
            "fcf_cagr_3yr": 0.05905483182741289
        },
        "valuation": {
            "pe_trailing": 14.651358,
            "pe_forward": 10.454203,
            "ps_ratio": 0.5642332,
            "pb_ratio": 3.9625092,
            "ev_ebitda": 9.028,
            "peg_ratio": 0.8158,
            "fcf_yield": 0.04922350632434859
        },
        "data_quality_flags": [
            "ACM: eps_cagr_3yr approximated by net income CAGR (share count changes not adjusted)"
        ]
    },
    "financial_raw_metrics_date": "2026-05-21",
    "financial_score": 52.52907508019581,
    "financial_score_date": "2026-05-21",
    "financial_subscores": {
        "profitability": 29.999569859106412,
        "returns_on_capital": 47.22195975153038,
        "cash_flow_quality": 41.626921606269065,
        "balance_sheet": 65.02520893744372,
        "growth": 61.438394027712306,
        "valuation": 79.14126981569792
    },
    "financial_drivers": {
        "strongest": [
            "eps_growth_1yr (growth): score=91, value=28.5%",
            "pe_forward (valuation): score=89, value=10.45",
            "eps_cagr_3yr (growth): score=86, value=21.8%"
        ],
        "weakest": [
            "gross_margin_ttm (profitability): score=14, value=7.7%",
            "fcf_margin_ttm (cash_flow_quality): score=24, value=2.8%",
            "net_margin_ttm (profitability): score=28, value=3.2%"
        ]
    },
    "professional_raw_metrics": {
        "sector": "Industrials",
        "industry": "Engineering & Construction",
        "market_cap_usd": 9019738112,
        "current_price": 70.18,
        "analyst": {
            "recommendation_mean": 1.46154,
            "recommendation_key": "strong_buy",
            "target_mean_price": 106.875,
            "target_median_price": 105.0,
            "target_high_price": 145.0,
            "target_low_price": 90.0,
            "upside_to_target": 0.5228697634653746,
            "target_dispersion": 0.5146198830409356,
            "num_analysts": 12
        },
        "rating_momentum": {
            "upgrades_12m": 0,
            "downgrades_12m": 2,
            "total_actions_12m": 36
        },
        "institutional": {
            "held_pct_institutions": 0.9358,
            "held_pct_insiders": 0.0049
        },
        "short_interest": {
            "short_pct_of_float": 0.060700003,
            "short_ratio": 5.34,
            "short_change_pct": 0.11738266258035608
        },
        "data_quality_flags": []
    },
    "professional_raw_metrics_date": "2026-05-21",
    "professional_score": 68.47205502333125,
    "professional_score_date": "2026-05-21",
    "professional_subscores": {
        "analyst_consensus": 94.46152000000001,
        "rating_momentum": 49.0,
        "institutional_positioning": 65.6736251381644,
        "short_interest": 44.94744492526766
    },
    "professional_drivers": {
        "strongest": [
            "upside_to_target (analyst_consensus): score=100, value=52.3%",
            "recommendation_mean (analyst_consensus): score=91, value=1.46",
            "held_pct_institutions (institutional_positioning): score=70, value=93.6%"
        ],
        "weakest": [
            "short_change_pct (short_interest): score=35, value=11.7%",
            "short_pct_of_float (short_interest): score=47, value=6.1%",
            "short_ratio (short_interest): score=48, value=5.34"
        ]
    },
    "news_sentiment_raw_metrics": {
        "sector": null,
        "industry": null,
        "market_cap_usd": null,
        "current_price": null,
        "earnings": {
            "beat_count_4q": 4,
            "miss_count_4q": 0,
            "total_quarters_4q": 4,
            "avg_surprise_magnitude_4q": 0.05573848365279147,
            "eps_estimate_revision_90d": null,
            "trailing_eps": null,
            "forward_eps": null
        },
        "price_momentum": {
            "return_1m": null,
            "return_3m": null,
            "return_6m": null
        },
        "insider_activity": {
            "insider_purchases_count_90d": null,
            "insider_sales_count_90d": null,
            "insider_net_value_90d_usd": null
        },
        "data_quality_flags": [
            "ACM: failed to fetch .info (Too Many Requests. Rate limited. Try after a while.)",
            "ACM: sector classification unavailable",
            "ACM: eps_revisions fetch failed (Too Many Requests. Rate limited. Try after a while.)",
            "ACM: price momentum fetch failed (Too Many Requests. Rate limited. Try after a while.)",
            "ACM: insider_transactions fetch failed (Too Many Requests. Rate limited. Try after a while.)"
        ]
    },
    "news_sentiment_raw_metrics_date": "2026-05-21",
    "news_sentiment_score": null,
    "news_sentiment_score_date": "2026-05-21",
    "news_sentiment_subscores": {
        "earnings_surprise_revisions": 89.25609773654037,
        "price_momentum": null,
        "insider_activity": null
    },
    "news_sentiment_drivers": {
        "strongest": [
            "beat_rate_4q (earnings_surprise_revisions): score=100, value=1.00",
            "avg_surprise_magnitude_4q (earnings_surprise_revisions): score=77, value=5.6%"
        ],
        "weakest": [
            "avg_surprise_magnitude_4q (earnings_surprise_revisions): score=77, value=5.6%",
            "beat_rate_4q (earnings_surprise_revisions): score=100, value=1.00"
        ]
    },
    "composite_score": 56.230212351310186,
    "composite_score_date": "2026-05-21",
    "composite_rank": 362,
    "composite_metadata": {
        "scores_used": [
            "financial",
            "professional"
        ],
        "scores_imputed": [
            "news_sentiment"
        ],
        "imputed_values": {
            "news_sentiment": 47.12029152106452
        },
        "imputation_r_squared": 0.05693184104207816,
        "weights_applied": {
            "financial": 50,
            "professional": 30,
            "news_sentiment": 20
        }
    }
}