{
    "ticker": "LFUS",
    "company_name": "Littelfuse",
    "universe_added_date": "2026-05-18",
    "financial_raw_metrics": {
        "sector": "Technology",
        "industry": "Electronic Components",
        "market_cap_usd": 11645034496,
        "profitability": {
            "gross_margin_ttm": 0.38568002,
            "operating_margin_ttm": 0.17296,
            "net_margin_ttm": -0.01612,
            "operating_margin_trend_3yr": -0.05334511579942869
        },
        "returns_on_capital": {
            "roe_ttm": -0.016139999,
            "roa_ttm": 0.06363,
            "roic_ttm": null
        },
        "cash_flow": {
            "fcf_margin_ttm": 0.13150489627959275,
            "fcf_to_net_income_ttm": -8.157459076861729,
            "ocf_cagr_3yr": 0.011032935575233438
        },
        "balance_sheet": {
            "debt_to_equity": 0.28318,
            "net_debt_to_ebitda": 0.429315295657866,
            "current_ratio": 2.61,
            "interest_coverage": 1.1051511529603826,
            "total_debt_usd": 711926016,
            "total_cash_usd": 483689984
        },
        "growth": {
            "revenue_growth_1yr": 0.185,
            "revenue_cagr_3yr": -0.01721431237859039,
            "eps_growth_1yr": 0.691,
            "eps_cagr_3yr": null,
            "fcf_cagr_3yr": 0.05099483030693164
        },
        "valuation": {
            "pe_trailing": null,
            "pe_forward": 26.671303,
            "ps_ratio": 4.6786823,
            "pb_ratio": 4.6088095,
            "ev_ebitda": 22.334,
            "peg_ratio": 2.7179,
            "fcf_yield": 0.028107249326949524
        },
        "data_quality_flags": [
            "LFUS: eps_cagr_3yr approximated by net income CAGR (share count changes not adjusted)"
        ]
    },
    "financial_raw_metrics_date": "2026-05-25",
    "financial_score": 45.40884474283214,
    "financial_score_date": "2026-05-25",
    "financial_subscores": {
        "profitability": 32.06356405722564,
        "returns_on_capital": 41.10785690543409,
        "cash_flow_quality": 36.925332983442736,
        "balance_sheet": 80.2988819448131,
        "growth": 48.315705838359726,
        "valuation": 39.6238162353857
    },
    "financial_drivers": {
        "strongest": [
            "eps_growth_1yr (growth): score=100, value=69.1%",
            "current_ratio (balance_sheet): score=95, value=2.61",
            "net_debt_to_ebitda (balance_sheet): score=94, value=42.9%"
        ],
        "weakest": [
            "fcf_to_net_income_ttm (cash_flow_quality): score=0, value=-8.16",
            "interest_coverage (balance_sheet): score=3, value=1.11",
            "revenue_cagr_3yr (growth): score=17, value=-1.7%"
        ]
    },
    "professional_raw_metrics": {
        "sector": "Technology",
        "industry": "Electronic Components",
        "market_cap_usd": 11645034496,
        "current_price": 460.48,
        "analyst": {
            "recommendation_mean": 1.75,
            "recommendation_key": "buy",
            "target_mean_price": 477.5,
            "target_median_price": 500.0,
            "target_high_price": 520.0,
            "target_low_price": 390.0,
            "upside_to_target": 0.03696143154968724,
            "target_dispersion": 0.27225130890052357,
            "num_analysts": 4
        },
        "rating_momentum": {
            "upgrades_12m": 2,
            "downgrades_12m": 0,
            "total_actions_12m": 9
        },
        "institutional": {
            "held_pct_institutions": 0.010516300000000001,
            "held_pct_insiders": 0.013890001
        },
        "short_interest": {
            "short_pct_of_float": 0.0276,
            "short_ratio": 2.76,
            "short_change_pct": -0.2215891877658031
        },
        "data_quality_flags": []
    },
    "professional_raw_metrics_date": "2026-05-25",
    "professional_score": 50.894803110622696,
    "professional_score_date": "2026-05-25",
    "professional_subscores": {
        "analyst_consensus": 44.754760250173725,
        "rating_momentum": 63.33333333333333,
        "institutional_positioning": 33.31681881563659,
        "short_interest": 73.78732657212944
    },
    "professional_drivers": {
        "strongest": [
            "recommendation_mean (analyst_consensus): score=82, value=1.75",
            "short_change_pct (short_interest): score=81, value=-22.2%",
            "short_ratio (short_interest): score=72, value=2.76"
        ],
        "weakest": [
            "held_pct_institutions (institutional_positioning): score=21, value=1.1%",
            "upside_to_target (analyst_consensus): score=36, value=3.7%",
            "held_pct_insiders (institutional_positioning): score=62, value=1.4%"
        ]
    },
    "news_sentiment_raw_metrics": {
        "sector": null,
        "industry": null,
        "market_cap_usd": null,
        "current_price": null,
        "earnings": {
            "beat_count_4q": null,
            "miss_count_4q": null,
            "total_quarters_4q": null,
            "avg_surprise_magnitude_4q": null,
            "eps_estimate_revision_90d": null,
            "trailing_eps": null,
            "forward_eps": null
        },
        "price_momentum": {
            "return_1m": 0.1690889471689725,
            "return_3m": 0.2697203722132267,
            "return_6m": 0.9675593483364915
        },
        "insider_activity": {
            "insider_purchases_count_90d": null,
            "insider_sales_count_90d": null,
            "insider_net_value_90d_usd": null
        },
        "data_quality_flags": [
            "LFUS: failed to fetch .info (Too Many Requests. Rate limited. Try after a while.)",
            "LFUS: sector classification unavailable",
            "LFUS: earnings_dates fetch failed (['Earnings Date'])",
            "LFUS: eps_revisions fetch failed (Too Many Requests. Rate limited. Try after a while.)",
            "LFUS: insider_transactions fetch failed (Too Many Requests. Rate limited. Try after a while.)"
        ]
    },
    "news_sentiment_raw_metrics_date": "2026-05-25",
    "news_sentiment_score": null,
    "news_sentiment_score_date": "2026-05-25",
    "news_sentiment_subscores": {
        "earnings_surprise_revisions": null,
        "price_momentum": 92.77906117781208,
        "insider_activity": null
    },
    "news_sentiment_drivers": {
        "strongest": [
            "return_6m (price_momentum): score=100, value=96.8%",
            "return_3m (price_momentum): score=95, value=27.0%",
            "return_1m (price_momentum): score=78, value=16.9%"
        ],
        "weakest": [
            "return_1m (price_momentum): score=78, value=16.9%",
            "return_3m (price_momentum): score=95, value=27.0%",
            "return_6m (price_momentum): score=100, value=96.8%"
        ]
    },
    "composite_score": 48.677204689399204,
    "composite_score_date": "2026-05-25",
    "composite_rank": 806,
    "composite_metadata": {
        "scores_used": [
            "financial",
            "professional"
        ],
        "scores_imputed": [
            "news_sentiment"
        ],
        "imputed_values": {
            "news_sentiment": 53.52170692398165
        },
        "imputation_r_squared": 0.031937368103860275,
        "weights_applied": {
            "financial": 50,
            "professional": 30,
            "news_sentiment": 20
        }
    }
}