{
    "ticker": "TJX",
    "company_name": "TJX Companies",
    "universe_added_date": "2026-05-18",
    "financial_raw_metrics": {
        "sector": "Consumer Cyclical",
        "industry": "Apparel Retail",
        "market_cap_usd": 163030188032,
        "profitability": {
            "gross_margin_ttm": 0.30963,
            "operating_margin_ttm": 0.13267,
            "net_margin_ttm": 0.091000006,
            "operating_margin_trend_3yr": 0.021571601579127492
        },
        "returns_on_capital": {
            "roe_ttm": 0.59129,
            "roa_ttm": 0.13289,
            "roic_ttm": null
        },
        "cash_flow": {
            "fcf_margin_ttm": 0.06446697062362299,
            "fcf_to_net_income_ttm": 0.7084091571393571,
            "ocf_cagr_3yr": 0.18952780522156587
        },
        "balance_sheet": {
            "debt_to_equity": 1.32375,
            "net_debt_to_ebitda": 0.8616024184145465,
            "current_ratio": 1.138,
            "interest_coverage": 99.63513513513513,
            "total_debt_usd": 13489000448,
            "total_cash_usd": 6230000128
        },
        "growth": {
            "revenue_growth_1yr": 0.085,
            "revenue_cagr_3yr": 0.06530493123671799,
            "eps_growth_1yr": 0.279,
            "eps_cagr_3yr": 0.16240182545565118,
            "fcf_cagr_3yr": 0.23238587451971782
        },
        "valuation": {
            "pe_trailing": 30.2731,
            "pe_forward": 25.993189,
            "ps_ratio": 2.700427,
            "pb_ratio": 16.018034,
            "ev_ebitda": 20.23,
            "peg_ratio": 3.3854,
            "fcf_yield": 0.02387287929298142
        },
        "data_quality_flags": [
            "TJX: eps_cagr_3yr approximated by net income CAGR (share count changes not adjusted)"
        ]
    },
    "financial_raw_metrics_date": "2026-05-18",
    "financial_score": 59.01071554458295,
    "financial_score_date": "2026-05-18",
    "financial_subscores": {
        "profitability": 54.44134570259026,
        "returns_on_capital": 63.26906865231827,
        "cash_flow_quality": 55.332316546755756,
        "balance_sheet": 75.33934960178908,
        "growth": 71.21671626985089,
        "valuation": 34.56916873894593
    },
    "financial_drivers": {
        "strongest": [
            "interest_coverage (balance_sheet): score=100, value=99.64",
            "eps_growth_1yr (growth): score=91, value=27.9%",
            "net_debt_to_ebitda (balance_sheet): score=89, value=86.2%"
        ],
        "weakest": [
            "peg_ratio (valuation): score=8, value=3.39",
            "pe_trailing (valuation): score=35, value=30.27",
            "fcf_yield (valuation): score=36, value=2.4%"
        ]
    },
    "professional_raw_metrics": {
        "sector": "Consumer Cyclical",
        "industry": "Apparel Retail",
        "market_cap_usd": 163030188032,
        "current_price": 147.43,
        "analyst": {
            "recommendation_mean": 1.45,
            "recommendation_key": "strong_buy",
            "target_mean_price": 172.16667,
            "target_median_price": 175.0,
            "target_high_price": 193.0,
            "target_low_price": 107.0,
            "upside_to_target": 0.1677858644780574,
            "target_dispersion": 0.49951596322331143,
            "num_analysts": 18
        },
        "rating_momentum": {
            "upgrades_12m": 0,
            "downgrades_12m": 0,
            "total_actions_12m": 55
        },
        "institutional": {
            "held_pct_institutions": 0.93813,
            "held_pct_insiders": 0.00168
        },
        "short_interest": {
            "short_pct_of_float": 0.0137,
            "short_ratio": 3.77,
            "short_change_pct": 0.1874484182945393
        },
        "data_quality_flags": []
    },
    "professional_raw_metrics_date": "2026-05-18",
    "professional_score": 67.86090119227872,
    "professional_score_date": "2026-05-18",
    "professional_subscores": {
        "analyst_consensus": 81.78572429853716,
        "rating_momentum": 52.5,
        "institutional_positioning": 68.04019682466007,
        "short_interest": 60.67232321083794
    },
    "professional_drivers": {
        "strongest": [
            "recommendation_mean (analyst_consensus): score=91, value=1.45",
            "held_pct_institutions (institutional_positioning): score=75, value=93.8%",
            "short_pct_of_float (short_interest): score=73, value=1.4%"
        ],
        "weakest": [
            "short_change_pct (short_interest): score=27, value=18.7%",
            "held_pct_insiders (institutional_positioning): score=52, value=0.2%",
            "upgrades_12m (rating_momentum): score=52, value=0.00"
        ]
    },
    "news_sentiment_raw_metrics": {
        "sector": "Consumer Cyclical",
        "industry": "Apparel Retail",
        "market_cap_usd": 163030188032,
        "current_price": 147.43,
        "earnings": {
            "beat_count_4q": null,
            "miss_count_4q": null,
            "total_quarters_4q": null,
            "avg_surprise_magnitude_4q": null,
            "eps_estimate_revision_90d": null,
            "trailing_eps": 4.87,
            "forward_eps": 5.67187
        },
        "price_momentum": {
            "return_1m": -0.07687140873817933,
            "return_3m": -0.04064801620993719,
            "return_6m": 0.0131903327818551
        },
        "insider_activity": {
            "insider_purchases_count_90d": 1,
            "insider_sales_count_90d": 1,
            "insider_net_value_90d_usd": -4827766.0
        },
        "data_quality_flags": [
            "TJX: earnings_dates fetch failed (['Earnings Date'])"
        ]
    },
    "news_sentiment_raw_metrics_date": "2026-05-18",
    "news_sentiment_score": 46.69742309738773,
    "news_sentiment_score_date": "2026-05-18",
    "news_sentiment_subscores": {
        "earnings_surprise_revisions": null,
        "price_momentum": 45.30524587578653,
        "insider_activity": 49.48177754059011
    },
    "news_sentiment_drivers": {
        "strongest": [
            "return_6m (price_momentum): score=52, value=1.3%",
            "insider_count_ratio_90d (insider_activity): score=50, value=0.00",
            "net_insider_value_pct_mcap_90d (insider_activity): score=49, value=-0.0%"
        ],
        "weakest": [
            "return_1m (price_momentum): score=37, value=-7.7%",
            "return_3m (price_momentum): score=43, value=-4.1%",
            "net_insider_value_pct_mcap_90d (insider_activity): score=49, value=-0.0%"
        ]
    },
    "composite_score": 59.203112749452636,
    "composite_score_date": "2026-05-18",
    "composite_rank": 260,
    "composite_metadata": {
        "scores_used": [
            "financial",
            "professional",
            "news_sentiment"
        ],
        "scores_imputed": [],
        "imputed_values": {},
        "imputation_r_squared": null,
        "weights_applied": {
            "financial": 50,
            "professional": 30,
            "news_sentiment": 20
        }
    }
}