{
    "ticker": "SNDK",
    "company_name": "SanDisk",
    "universe_added_date": "2026-05-18",
    "financial_raw_metrics": {
        "sector": "Technology",
        "industry": "Computer Hardware",
        "market_cap_usd": 218977370112,
        "profitability": {
            "gross_margin_ttm": 0.56038,
            "operating_margin_ttm": 0.69983,
            "net_margin_ttm": 0.34185,
            "operating_margin_trend_3yr": null
        },
        "returns_on_capital": {
            "roe_ttm": 0.39297,
            "roa_ttm": 0.22823,
            "roic_ttm": null
        },
        "cash_flow": {
            "fcf_margin_ttm": 0.17138198058252427,
            "fcf_to_net_income_ttm": 0.5013312909375656,
            "ocf_cagr_3yr": null
        },
        "balance_sheet": {
            "debt_to_equity": 0.015029999999999998,
            "net_debt_to_ebitda": -0.626420465909091,
            "current_ratio": 4.782,
            "interest_coverage": -22.476190476190474,
            "total_debt_usd": 207000000,
            "total_cash_usd": 3735000064
        },
        "growth": {
            "revenue_growth_1yr": 2.51,
            "revenue_cagr_3yr": null,
            "eps_growth_1yr": null,
            "eps_cagr_3yr": null,
            "fcf_cagr_3yr": null
        },
        "valuation": {
            "pe_trailing": 50.501366,
            "pe_forward": 8.431499,
            "ps_ratio": 16.609327,
            "pb_ratio": 21.42797,
            "ev_ebitda": 38.255,
            "peg_ratio": null,
            "fcf_yield": 0.010318417975539377
        },
        "data_quality_flags": []
    },
    "financial_raw_metrics_date": "2026-05-25",
    "financial_score": 64.37105636222338,
    "financial_score_date": "2026-05-25",
    "financial_subscores": {
        "profitability": 61.783234844122425,
        "returns_on_capital": 71.2212739202046,
        "cash_flow_quality": 60.85542190521505,
        "balance_sheet": 83.712425,
        "growth": null,
        "valuation": 42.86212746161477
    },
    "financial_drivers": {
        "strongest": [
            "revenue_growth_1yr (growth): score=100, value=2.51",
            "current_ratio (balance_sheet): score=100, value=4.78",
            "net_debt_to_ebitda (balance_sheet): score=100, value=-62.6%"
        ],
        "weakest": [
            "interest_coverage (balance_sheet): score=0, value=-22.48",
            "pe_trailing (valuation): score=10, value=50.50",
            "fcf_yield (valuation): score=20, value=1.0%"
        ]
    },
    "professional_raw_metrics": {
        "sector": "Technology",
        "industry": "Computer Hardware",
        "market_cap_usd": 218977370112,
        "current_price": 1478.68,
        "analyst": {
            "recommendation_mean": 1.59091,
            "recommendation_key": "buy",
            "target_mean_price": 1493.3636,
            "target_median_price": 1400.0,
            "target_high_price": 2350.0,
            "target_low_price": 1000.0,
            "upside_to_target": 0.00993020802337209,
            "target_dispersion": 0.9039995350094244,
            "num_analysts": 22
        },
        "rating_momentum": {
            "upgrades_12m": 0,
            "downgrades_12m": 0,
            "total_actions_12m": 68
        },
        "institutional": {
            "held_pct_institutions": 0.807,
            "held_pct_insiders": 0.055019997
        },
        "short_interest": {
            "short_pct_of_float": 0.1141,
            "short_ratio": 0.68,
            "short_change_pct": 0.34277365198408283
        },
        "data_quality_flags": []
    },
    "professional_raw_metrics_date": "2026-05-25",
    "professional_score": 60.617358861534825,
    "professional_score_date": "2026-05-25",
    "professional_subscores": {
        "analyst_consensus": 63.55524496280465,
        "rating_momentum": 52.5,
        "institutional_positioning": 71.63659928744555,
        "short_interest": 48.92582201794533
    },
    "professional_drivers": {
        "strongest": [
            "short_ratio (short_interest): score=93, value=68.0%",
            "recommendation_mean (analyst_consensus): score=87, value=1.59",
            "held_pct_insiders (institutional_positioning): score=81, value=5.5%"
        ],
        "weakest": [
            "short_change_pct (short_interest): score=13, value=34.3%",
            "upside_to_target (analyst_consensus): score=28, value=1.0%",
            "short_pct_of_float (short_interest): score=37, value=11.4%"
        ]
    },
    "news_sentiment_raw_metrics": {
        "sector": null,
        "industry": null,
        "market_cap_usd": null,
        "current_price": null,
        "earnings": {
            "beat_count_4q": null,
            "miss_count_4q": null,
            "total_quarters_4q": null,
            "avg_surprise_magnitude_4q": null,
            "eps_estimate_revision_90d": null,
            "trailing_eps": null,
            "forward_eps": null
        },
        "price_momentum": {
            "return_1m": 0.5103005202329544,
            "return_3m": 1.3807980767180306,
            "return_6m": 6.5458761519914255
        },
        "insider_activity": {
            "insider_purchases_count_90d": null,
            "insider_sales_count_90d": null,
            "insider_net_value_90d_usd": null
        },
        "data_quality_flags": [
            "SNDK: failed to fetch .info (Too Many Requests. Rate limited. Try after a while.)",
            "SNDK: sector classification unavailable",
            "SNDK: earnings_dates fetch failed (['Earnings Date'])",
            "SNDK: insider_transactions fetch failed (Too Many Requests. Rate limited. Try after a while.)"
        ]
    },
    "news_sentiment_raw_metrics_date": "2026-05-25",
    "news_sentiment_score": null,
    "news_sentiment_score_date": "2026-05-25",
    "news_sentiment_subscores": {
        "earnings_surprise_revisions": null,
        "price_momentum": 100.0,
        "insider_activity": null
    },
    "news_sentiment_drivers": {
        "strongest": [
            "return_6m (price_momentum): score=100, value=6.55",
            "return_3m (price_momentum): score=100, value=1.38",
            "return_1m (price_momentum): score=100, value=51.0%"
        ],
        "weakest": [
            "return_1m (price_momentum): score=100, value=51.0%",
            "return_3m (price_momentum): score=100, value=1.38",
            "return_6m (price_momentum): score=100, value=6.55"
        ]
    },
    "composite_score": 60.22004727935184,
    "composite_score_date": "2026-05-25",
    "composite_rank": 195,
    "composite_metadata": {
        "scores_used": [
            "financial",
            "professional"
        ],
        "scores_imputed": [
            "news_sentiment"
        ],
        "imputed_values": {
            "news_sentiment": 49.246557198898465
        },
        "imputation_r_squared": 0.031937368103860275,
        "weights_applied": {
            "financial": 50,
            "professional": 30,
            "news_sentiment": 20
        }
    },
    "disqualifier_flags": {
        "bankruptcy_8k": {
            "triggered": false
        },
        "material_restatement_10ka": {
            "triggered": false
        },
        "check_status": "ok",
        "error_message": null
    },
    "disqualifier_check_date": "2026-05-21",
    "qualified": true
}