{
    "ticker": "FHN",
    "company_name": "First Horizon Corporation",
    "universe_added_date": "2026-05-18",
    "financial_raw_metrics": {
        "sector": "Financial Services",
        "industry": "Banks - Regional",
        "market_cap_usd": 11438289920,
        "profitability": {
            "gross_margin_ttm": 0.0,
            "operating_margin_ttm": 0.42856997,
            "net_margin_ttm": 0.29920998,
            "operating_margin_trend_3yr": null
        },
        "returns_on_capital": {
            "roe_ttm": 0.11259,
            "roa_ttm": 0.01258,
            "roic_ttm": null
        },
        "cash_flow": {
            "fcf_margin_ttm": null,
            "fcf_to_net_income_ttm": null,
            "ocf_cagr_3yr": -0.3504017421341993
        },
        "balance_sheet": {
            "debt_to_equity": null,
            "net_debt_to_ebitda": null,
            "current_ratio": null,
            "interest_coverage": null,
            "total_debt_usd": 5900000256,
            "total_cash_usd": 4906999808
        },
        "growth": {
            "revenue_growth_1yr": 0.097,
            "revenue_cagr_3yr": 0.021233961726539796,
            "eps_growth_1yr": 0.293,
            "eps_cagr_3yr": 0.029492039447090335,
            "fcf_cagr_3yr": -0.3593647905175772
        },
        "valuation": {
            "pe_trailing": 12.110553,
            "pe_forward": 10.259074,
            "ps_ratio": 3.335751,
            "pb_ratio": 1.3609668,
            "ev_ebitda": null,
            "peg_ratio": 1.76,
            "fcf_yield": null
        },
        "data_quality_flags": [
            "FHN: eps_cagr_3yr approximated by net income CAGR (share count changes not adjusted)"
        ]
    },
    "financial_raw_metrics_date": "2026-05-21",
    "financial_score": 51.3791854918932,
    "financial_score_date": "2026-05-21",
    "financial_subscores": {
        "profitability": 48.36917597769398,
        "returns_on_capital": 48.25529390686306,
        "cash_flow_quality": null,
        "balance_sheet": null,
        "growth": 36.5583170554862,
        "valuation": 74.37858872727273
    },
    "financial_drivers": {
        "strongest": [
            "eps_growth_1yr (growth): score=92, value=29.3%",
            "pe_forward (valuation): score=89, value=10.26",
            "pe_trailing (valuation): score=84, value=12.11"
        ],
        "weakest": [
            "ocf_cagr_3yr (cash_flow_quality): score=0, value=-35.0%",
            "fcf_cagr_3yr (growth): score=0, value=-35.9%",
            "eps_cagr_3yr (growth): score=32, value=2.9%"
        ]
    },
    "professional_raw_metrics": {
        "sector": "Financial Services",
        "industry": "Banks - Regional",
        "market_cap_usd": 11438289920,
        "current_price": 24.1,
        "analyst": {
            "recommendation_mean": null,
            "recommendation_key": "none",
            "target_mean_price": 26.84211,
            "target_median_price": 26.0,
            "target_high_price": 30.0,
            "target_low_price": 25.0,
            "upside_to_target": 0.11378049792531121,
            "target_dispersion": 0.18627447693195504,
            "num_analysts": 19
        },
        "rating_momentum": {
            "upgrades_12m": 0,
            "downgrades_12m": 3,
            "total_actions_12m": 43
        },
        "institutional": {
            "held_pct_institutions": 0.88799006,
            "held_pct_insiders": 0.00963
        },
        "short_interest": {
            "short_pct_of_float": 0.0001,
            "short_ratio": 0.0,
            "short_change_pct": -0.9100482890875904
        },
        "data_quality_flags": []
    },
    "professional_raw_metrics_date": "2026-05-21",
    "professional_score": 59.8563043536463,
    "professional_score_date": "2026-05-21",
    "professional_subscores": {
        "analyst_consensus": 55.9451244813278,
        "rating_momentum": 48.1046511627907,
        "institutional_positioning": 59.95924504583823,
        "short_interest": 88.39691155349558
    },
    "professional_drivers": {
        "strongest": [
            "short_change_pct (short_interest): score=100, value=-91.0%",
            "short_ratio (short_interest): score=100, value=0.00",
            "short_pct_of_float (short_interest): score=77, value=0.0%"
        ],
        "weakest": [
            "upgrades_12m (rating_momentum): score=48, value=0.00",
            "downgrades_12m (rating_momentum): score=48, value=3.00",
            "total_actions_12m (rating_momentum): score=48, value=43.00"
        ]
    },
    "news_sentiment_raw_metrics": {
        "sector": "Financial Services",
        "industry": "Banks - Regional",
        "market_cap_usd": 11438289920,
        "current_price": 24.1,
        "earnings": {
            "beat_count_4q": null,
            "miss_count_4q": null,
            "total_quarters_4q": null,
            "avg_surprise_magnitude_4q": null,
            "eps_estimate_revision_90d": null,
            "trailing_eps": 1.99,
            "forward_eps": 2.34914
        },
        "price_momentum": {
            "return_1m": -0.023104988833853795,
            "return_3m": -0.03242126085701649,
            "return_6m": 0.14630533121478967
        },
        "insider_activity": {
            "insider_purchases_count_90d": 0,
            "insider_sales_count_90d": 0,
            "insider_net_value_90d_usd": null
        },
        "data_quality_flags": [
            "FHN: earnings_dates fetch failed (['Earnings Date'])"
        ]
    },
    "news_sentiment_raw_metrics_date": "2026-05-21",
    "news_sentiment_score": 54.59982710861074,
    "news_sentiment_score_date": "2026-05-21",
    "news_sentiment_subscores": {
        "earnings_surprise_revisions": null,
        "price_momentum": 56.89974066291611,
        "insider_activity": 50.0
    },
    "news_sentiment_drivers": {
        "strongest": [
            "return_6m (price_momentum): score=74, value=14.6%",
            "insider_activity_summary (insider_activity): score=50, value=no activity in 90d",
            "return_1m (price_momentum): score=46, value=-2.3%"
        ],
        "weakest": [
            "return_3m (price_momentum): score=45, value=-3.2%",
            "return_1m (price_momentum): score=46, value=-2.3%",
            "insider_activity_summary (insider_activity): score=50, value=no activity in 90d"
        ]
    },
    "composite_score": 54.56644947376263,
    "composite_score_date": "2026-05-21",
    "composite_rank": 465,
    "composite_metadata": {
        "scores_used": [
            "financial",
            "professional",
            "news_sentiment"
        ],
        "scores_imputed": [],
        "imputed_values": {},
        "imputation_r_squared": null,
        "weights_applied": {
            "financial": 50,
            "professional": 30,
            "news_sentiment": 20
        }
    }
}