{
    "ticker": "CTVA",
    "company_name": "Corteva",
    "universe_added_date": "2026-05-18",
    "financial_raw_metrics": {
        "sector": "Basic Materials",
        "industry": "Agricultural Inputs",
        "market_cap_usd": 54983688192,
        "profitability": {
            "gross_margin_ttm": 0.48561,
            "operating_margin_ttm": 0.2369,
            "net_margin_ttm": 0.064959995,
            "operating_margin_trend_3yr": 0.040053134571117394
        },
        "returns_on_capital": {
            "roe_ttm": 0.051370002,
            "roa_ttm": 0.043270003,
            "roic_ttm": null
        },
        "cash_flow": {
            "fcf_margin_ttm": 0.14400609374182513,
            "fcf_to_net_income_ttm": 2.057607769968051,
            "ocf_cagr_3yr": 0.574862781730215
        },
        "balance_sheet": {
            "debt_to_equity": 0.1364,
            "net_debt_to_ebitda": 0.3356677183005878,
            "current_ratio": 1.467,
            "interest_coverage": 10.377777777777778,
            "total_debt_usd": 3356000000,
            "total_cash_usd": 1966000000
        },
        "growth": {
            "revenue_growth_1yr": 0.11,
            "revenue_cagr_3yr": -0.0010322883978914899,
            "eps_growth_1yr": 0.121,
            "eps_cagr_3yr": -0.015646020527176785,
            "fcf_cagr_3yr": 1.1927496276897047
        },
        "valuation": {
            "pe_trailing": 44.437836,
            "pe_forward": 20.092974,
            "ps_ratio": 3.0736034,
            "pb_ratio": 2.2886972,
            "ev_ebitda": 13.672,
            "peg_ratio": 1.3259,
            "fcf_yield": 0.04685253049966954
        },
        "data_quality_flags": [
            "CTVA: eps_cagr_3yr approximated by net income CAGR (share count changes not adjusted)"
        ]
    },
    "financial_raw_metrics_date": "2026-05-18",
    "financial_score": 61.39040633633209,
    "financial_score_date": "2026-05-18",
    "financial_subscores": {
        "profitability": 66.28001922384897,
        "returns_on_capital": 45.426854246415814,
        "cash_flow_quality": 74.34889681163516,
        "balance_sheet": 89.36910550239686,
        "growth": 47.16691218294709,
        "valuation": 49.44196311821512
    },
    "financial_drivers": {
        "strongest": [
            "fcf_cagr_3yr (growth): score=100, value=1.19",
            "ocf_cagr_3yr (cash_flow_quality): score=100, value=57.5%",
            "net_debt_to_ebitda (balance_sheet): score=96, value=33.6%"
        ],
        "weakest": [
            "pe_trailing (valuation): score=17, value=44.44",
            "eps_cagr_3yr (growth): score=18, value=-1.6%",
            "revenue_cagr_3yr (growth): score=20, value=-0.1%"
        ]
    },
    "professional_raw_metrics": {
        "sector": "Basic Materials",
        "industry": "Agricultural Inputs",
        "market_cap_usd": 54983688192,
        "current_price": 82.21,
        "analyst": {
            "recommendation_mean": 1.77273,
            "recommendation_key": "buy",
            "target_mean_price": 89.38095,
            "target_median_price": 90.0,
            "target_high_price": 100.0,
            "target_low_price": 77.0,
            "upside_to_target": 0.08722722296557603,
            "target_dispersion": 0.2573255263006267,
            "num_analysts": 21
        },
        "rating_momentum": {
            "upgrades_12m": 2,
            "downgrades_12m": 3,
            "total_actions_12m": 41
        },
        "institutional": {
            "held_pct_institutions": 0.89585,
            "held_pct_insiders": 0.00124
        },
        "short_interest": {
            "short_pct_of_float": 0.025799999,
            "short_ratio": 4.36,
            "short_change_pct": 0.08893998747458579
        },
        "data_quality_flags": []
    },
    "professional_raw_metrics_date": "2026-05-18",
    "professional_score": 61.45589196964251,
    "professional_score_date": "2026-05-18",
    "professional_subscores": {
        "analyst_consensus": 68.8135822965576,
        "rating_momentum": 50.96341463414634,
        "institutional_positioning": 63.507869894992396,
        "short_interest": 58.35544689041773
    },
    "professional_drivers": {
        "strongest": [
            "recommendation_mean (analyst_consensus): score=82, value=1.77",
            "held_pct_institutions (institutional_positioning): score=69, value=89.6%",
            "short_pct_of_float (short_interest): score=67, value=2.6%"
        ],
        "weakest": [
            "short_change_pct (short_interest): score=39, value=8.9%",
            "upside_to_target (analyst_consensus): score=49, value=8.7%",
            "upgrades_12m (rating_momentum): score=51, value=2.00"
        ]
    },
    "news_sentiment_raw_metrics": {
        "sector": "Basic Materials",
        "industry": "Agricultural Inputs",
        "market_cap_usd": 54983688192,
        "current_price": 82.21,
        "earnings": {
            "beat_count_4q": 3,
            "miss_count_4q": 0,
            "total_quarters_4q": 4,
            "avg_surprise_magnitude_4q": 0.1542094507816603,
            "eps_estimate_revision_90d": null,
            "trailing_eps": 1.85,
            "forward_eps": 4.09148
        },
        "price_momentum": {
            "return_1m": 0.010944420911408598,
            "return_3m": 0.11179475115516282,
            "return_6m": 0.24796862772348888
        },
        "insider_activity": {
            "insider_purchases_count_90d": 0,
            "insider_sales_count_90d": 1,
            "insider_net_value_90d_usd": -636200.0
        },
        "data_quality_flags": []
    },
    "news_sentiment_raw_metrics_date": "2026-05-18",
    "news_sentiment_score": 70.13297111270298,
    "news_sentiment_score_date": "2026-05-18",
    "news_sentiment_subscores": {
        "earnings_surprise_revisions": 84.42505157453817,
        "price_momentum": 73.50861987025912,
        "insider_activity": 34.79751267392026
    },
    "news_sentiment_drivers": {
        "strongest": [
            "avg_surprise_magnitude_4q (earnings_surprise_revisions): score=95, value=15.4%",
            "return_6m (price_momentum): score=91, value=24.8%",
            "beat_rate_4q (earnings_surprise_revisions): score=75, value=75.0%"
        ],
        "weakest": [
            "insider_count_ratio_90d (insider_activity): score=0, value=-1.00",
            "net_insider_value_pct_mcap_90d (insider_activity): score=50, value=-0.0%",
            "return_1m (price_momentum): score=52, value=1.1%"
        ]
    },
    "composite_score": 63.15856498159939,
    "composite_score_date": "2026-05-18",
    "composite_rank": 105,
    "composite_metadata": {
        "scores_used": [
            "financial",
            "professional",
            "news_sentiment"
        ],
        "scores_imputed": [],
        "imputed_values": {},
        "imputation_r_squared": null,
        "weights_applied": {
            "financial": 50,
            "professional": 30,
            "news_sentiment": 20
        }
    }
}